django_sqlite_file_cache/__init__.py
django_sqlite_file_cache-0.6.2.dist-info/LICENSE
django_sqlite_file_cache-0.6.2.dist-info/METADATA
django_sqlite_file_cache-0.6.2.dist-info/WHEEL
django_sqlite_file_cache-0.6.2.dist-info/top_level.txt
django_sqlite_file_cache-0.6.2.dist-info/RECORD
